jupyterlab_katex/__init__.py
jupyterlab_katex/_version.py
jupyterlab_katex-3.4.0.data/data/share/jupyter/labextensions/@jupyterlab/katex-extension/package.json
jupyterlab_katex-3.4.0.data/data/share/jupyter/labextensions/@jupyterlab/katex-extension/schemas/@jupyterlab/katex-extension/package.json.orig
jupyterlab_katex-3.4.0.data/data/share/jupyter/labextensions/@jupyterlab/katex-extension/schemas/@jupyterlab/katex-extension/plugin.json
jupyterlab_katex-3.4.0.data/data/share/jupyter/labextensions/@jupyterlab/katex-extension/static/01e074cc3dcd71407103.woff2
jupyterlab_katex-3.4.0.data/data/share/jupyter/labextensions/@jupyterlab/katex-extension/static/06af0fba8798a625f89e.ttf
jupyterlab_katex-3.4.0.data/data/share/jupyter/labextensions/@jupyterlab/katex-extension/static/081f08cf7e0a8a68cdbb.ttf
jupyterlab_katex-3.4.0.data/data/share/jupyter/labextensions/@jupyterlab/katex-extension/static/08f69ff860ef323f559c.woff
jupyterlab_katex-3.4.0.data/data/share/jupyter/labextensions/@jupyterlab/katex-extension/static/0b27467a453fa09303e0.woff2
jupyterlab_katex-3.4.0.data/data/share/jupyter/labextensions/@jupyterlab/katex-extension/static/0b9f6662c0c07fbd4c68.woff
jupyterlab_katex-3.4.0.data/data/share/jupyter/labextensions/@jupyterlab/katex-extension/static/10914c41ecc86f469415.woff
jupyterlab_katex-3.4.0.data/data/share/jupyter/labextensions/@jupyterlab/katex-extension/static/114d46ba510a4d816884.ttf
jupyterlab_katex-3.4.0.data/data/share/jupyter/labextensions/@jupyterlab/katex-extension/static/1182f7b49fead9d22f3f.woff
jupyterlab_katex-3.4.0.data/data/share/jupyter/labextensions/@jupyterlab/katex-extension/static/120253ea1310e3b80891.woff
jupyterlab_katex-3.4.0.data/data/share/jupyter/labextensions/@jupyterlab/katex-extension/static/14c6e060c8735876e3cd.woff
jupyterlab_katex-3.4.0.data/data/share/jupyter/labextensions/@jupyterlab/katex-extension/static/15978c32403fa18a1843.woff
jupyterlab_katex-3.4.0.dist-info/METADATA
jupyterlab_katex-3.4.0.dist-info/WHEEL
jupyterlab_katex-3.4.0.dist-info/licenses/LICENSE
jupyterlab_katex-3.4.0.dist-info/RECORD
